easykube/__init__.py
easykube/flow.py
easykube/py.typed
easykube/kubernetes/__init__.py
easykube/kubernetes/config.py
easykube/kubernetes/resources.py
easykube/kubernetes/client/__init__.py
easykube/kubernetes/client/api.py
easykube/kubernetes/client/client.py
easykube/kubernetes/client/errors.py
easykube/kubernetes/client/iterators.py
easykube/kubernetes/client/resource.py
easykube/kubernetes/client/spec.py
easykube/rest/__init__.py
easykube/rest/client.py
easykube/rest/iterators.py
easykube/rest/resource.py
easykube/rest/util.py
easykube-0.6.0.dist-info/licenses/LICENSE
easykube-0.6.0.dist-info/METADATA
easykube-0.6.0.dist-info/WHEEL
easykube-0.6.0.dist-info/top_level.txt
easykube-0.6.0.dist-info/RECORD
