Metadata-Version: 2.4
Name: easykube
Version: 0.6.0
Summary: Simple, asynchronous Python client for Kubernetes.
Home-page: https://github.com/azimuth-cloud/easykube
Author: Matt Pryor
Author-email: matt@stackhpc.com
License-File: LICENSE
Requires-Dist: certifi
Requires-Dist: httpx
Requires-Dist: pyyaml
Provides-Extra: socks
Requires-Dist: socksio==1.*; extra == "socks"
Dynamic: license-file
